alavida_x_scraper/__init__.py
alavida_x_scraper/client.py
alavida_x_scraper/environment.py
alavida_x_scraper/core/__init__.py
alavida_x_scraper/core/api_error.py
alavida_x_scraper/core/client_wrapper.py
alavida_x_scraper/core/datetime_utils.py
alavida_x_scraper/core/file.py
alavida_x_scraper/core/force_multipart.py
alavida_x_scraper/core/http_client.py
alavida_x_scraper/core/http_response.py
alavida_x_scraper/core/jsonable_encoder.py
alavida_x_scraper/core/pydantic_utilities.py
alavida_x_scraper/core/query_encoder.py
alavida_x_scraper/core/remove_none_from_dict.py
alavida_x_scraper/core/request_options.py
alavida_x_scraper/core/serialization.py
alavida_x_scraper/core/http_sse/__init__.py
alavida_x_scraper/core/http_sse/_api.py
alavida_x_scraper/core/http_sse/_decoders.py
alavida_x_scraper/core/http_sse/_exceptions.py
alavida_x_scraper/core/http_sse/_models.py
alavida_x_scraper/discovery/__init__.py
alavida_x_scraper/discovery/client.py
alavida_x_scraper/discovery/raw_client.py
alavida_x_scraper/errors/__init__.py
alavida_x_scraper/errors/bad_request_error.py
alavida_x_scraper/errors/not_found_error.py
alavida_x_scraper/errors/service_unavailable_error.py
alavida_x_scraper/errors/too_many_requests_error.py
alavida_x_scraper/errors/unauthorized_error.py
alavida_x_scraper/scraping/__init__.py
alavida_x_scraper/scraping/client.py
alavida_x_scraper/scraping/raw_client.py
alavida_x_scraper/scraping/types/__init__.py
alavida_x_scraper/scraping/types/scrape_user_params_query_type.py
alavida_x_scraper/scraping/types/scrape_user_params_replies_filter.py
alavida_x_scraper/types/__init__.py
alavida_x_scraper/types/cost.py
alavida_x_scraper/types/discover_accounts_metadata.py
alavida_x_scraper/types/discover_accounts_response.py
alavida_x_scraper/types/discovered_account.py
alavida_x_scraper/types/error_response.py
alavida_x_scraper/types/error_response_error.py
alavida_x_scraper/types/scrape_post_metadata.py
alavida_x_scraper/types/scrape_post_response.py
alavida_x_scraper-0.1.0.dist-info/METADATA
alavida_x_scraper-0.1.0.dist-info/WHEEL
alavida_x_scraper-0.1.0.dist-info/top_level.txt
alavida_x_scraper-0.1.0.dist-info/RECORD
