Metadata-Version: 2.4
Name: alavida-x-scraper
Version: 0.1.0
Summary: Alavida X Scraper SDK (Python).
License-Expression: MIT
Requires-Python: >=3.9
Requires-Dist: httpx>=0.27.0
Requires-Dist: pydantic>=2.0.0
Requires-Dist: typing-extensions>=4.7.0
